dagon/__init__.py
dagon/ar/__init__.py
dagon/ar/ar_test.py
dagon/ar/py.typed
dagon/cache/__init__.py
dagon/cache/cache_test.py
dagon/core/__init__.py
dagon/core/exec.py
dagon/core/exec_test.py
dagon/core/ll_dag.py
dagon/core/ll_dag_test.py
dagon/core/py.typed
dagon/core/result.py
dagon/db/__init__.py
dagon/db/db_test.py
dagon/db/py.typed
dagon/event/__init__.py
dagon/event/cancel.py
dagon/event/event.py
dagon/event/py.typed
dagon/event/test_event.py
dagon/ext/__init__.py
dagon/ext/base.py
dagon/ext/exec.py
dagon/ext/iface.py
dagon/ext/loader.py
dagon/ext/output.py
dagon/ext/py.typed
dagon/fs/__init__.py
dagon/fs/fs_test.py
dagon/fs/py.typed
dagon/http/__init__.py
dagon/http/_cache.py
dagon/http/_cache_test.py
dagon/http/http_test.py
dagon/http/py.typed
dagon/inspect/__init__.py
dagon/inspect/__main__.py
dagon/inspect/graph.py
dagon/inspect/main.py
dagon/inspect/py.typed
dagon/inspect/timeline.py
dagon/inspect/tl.css
dagon/inspect/tl.html
dagon/inspect/tl.js
dagon/option/__init__.py
dagon/option/option_test.py
dagon/option/py.typed
dagon/persist/__init__.py
dagon/persist/persist_test.py
dagon/persist/py.typed
dagon/pool/__init__.py
dagon/pool/py.typed
dagon/proc/__init__.py
dagon/proc/proc_test.py
dagon/proc/py.typed
dagon/script_mode/__init__.py
dagon/script_mode/py.typed
dagon/storage/__init__.py
dagon/storage/py.typed
dagon/storage/storage_test.py
dagon/task/__init__.py
dagon/task/dag.py
dagon/task/dag_test.py
dagon/task/py.typed
dagon/task/task.py
dagon/task/task_test.py
dagon/tool/__init__.py
dagon/tool/__main__.py
dagon/tool/args.py
dagon/tool/main.py
dagon/tool/py.typed
dagon/ui/__init__.py
dagon/ui/ansi.py
dagon/ui/events.py
dagon/ui/fancy.py
dagon/ui/iface.py
dagon/ui/message.py
dagon/ui/proc.py
dagon/ui/py.typed
dagon/ui/simple.py
dagon/ui/stdio_cap.py
dagon/util/__init__.py
dagon/util/doc.py
dagon/util/paths.py
dagon/util/py.typed
dagon/util/testing.py
dagon-0.10.1.dist-info/entry_points.txt
dagon-0.10.1.dist-info/WHEEL
dagon-0.10.1.dist-info/METADATA
dagon-0.10.1.dist-info/RECORD
